[
    {
        "iconUrl": "https://www.google.com/s2/favicons?sz=128&domain=https://adultdeepfakes.com",
        "apiVersion": 1,
        "repositoryUrl": "https://github.com/Kraptor123/Cs-GizliKeyif",
        "fileSize": 17373,
        "status": 1,
        "language": "en",
        "authors": [
            "kraptor"
        ],
        "tvTypes": [
            "NSFW"
        ],
        "version": 1,
        "internalName": "AdultDeepFakes",
        "description": "!Fake Videos! We are the best source of deepfake porn videos. We have the largest collection of celebrity porn deepfakes, featuring celebrities, youtubers, kpop singers, etc.",
        "url": "https://raw.githubusercontent.com/Kraptor123/Cs-GizliKeyif/builds/AdultDeepFakes.cs3",
        "name": "AdultDeepFakes"
    },
    {
        "iconUrl": "https://t0.gstatic.com/faviconV2?client=SOCIAL&type=FAVICON&fallback_opts=TYPE,SIZE,URL&url=https://adult-tv-channels.com&size=128",
        "apiVersion": 1,
        "repositoryUrl": "https://github.com/Kraptor123/Cs-GizliKeyif",
        "fileSize": 9211,
        "status": 1,
        "language": "en",
        "authors": [
            "kraptor"
        ],
        "tvTypes": [
            "NSFW"
        ],
        "version": 2,
        "internalName": "AdultTvChannels",
        "description": "Watch free adult TV channels online",
        "url": "https://raw.githubusercontent.com/Kraptor123/Cs-GizliKeyif/builds/AdultTvChannels.cs3",
        "name": "AdultTvChannels"
    },
    {
        "iconUrl": "https://t3.gstatic.com/faviconV2?client=SOCIAL&type=FAVICON&fallback_opts=TYPE,SIZE,URL&url=https://www.aflamk1.net&size=16",
        "apiVersion": 1,
        "repositoryUrl": "https://github.com/Kraptor123/Cs-GizliKeyif",
        "fileSize": 15923,
        "status": 1,
        "language": "ar",
        "authors": [
            "kraptor"
        ],
        "tvTypes": [
            "NSFW"
        ],
        "version": 2,
        "internalName": "Aflamk",
        "description": "Xnxx \u0627\u0641\u0644\u0627\u0645 \u0633\u0643\u0633 \u0639\u0631\u0628\u064a \u0648 \u0627\u062c\u0646\u0628\u0649 \u0633\u0643\u0633 \u0646\u0633\u0648\u0627\u0646\u062c\u0649 \u0645\u062d\u062c\u0628\u0627\u062a \u0633\u0643\u0633 \u0645\u062a\u0631\u062c\u0645 \u0639\u0631\u0628\u0649 \u0627\u062d\u062a\u0631\u0627\u0641\u0649 \u0645\u062a\u0631\u062c\u0645\u0629 \u0639\u0627\u0644\u0645\u0649 \u0645\u062d\u062c\u0628\u0629 \u0633\u0643\u0633 \u062c\u0645\u0627\u0639\u0649 \u0627\u0645\u0647\u0627\u062a \u0645\u062d\u0627\u0631\u0645 \u0627\u0644\u0627\u0645 \u0645\u0635\u0631\u0649 \u0635\u0648\u0631 \u0645\u0642\u0627\u0637\u0639 \u0627\u062e \u0648\u0627\u062e\u062a\u0629 \u062e\u0644\u064a\u062c\u0649 \u062a\u062d\u0631\u0634 \u0648\u0639\u0646\u0641 \u0646\u064a\u0643 \u0627\u062e\u062a \u0627\u062e\u062a\u0649 \u062c\u0648\u0631\u062f\u0649 \u0645\u0631\u0627\u062a \u0627\u0644\u0623\u0628 \u0628\u0631\u0627\u0632\u0631 \u0633\u062d\u0627\u0642 \u062e\u064a\u0627\u0646\u0629 \u062d\u0645\u0627\u062a\u0649 \u0627\u0645\u0649  \u0645\u062d\u0631\u0645 \u0646\u064a\u0643.",
        "url": "https://raw.githubusercontent.com/Kraptor123/Cs-GizliKeyif/builds/Aflamk.cs3",
        "name": "Aflamk"
    },
    {
        "iconUrl": "https://t3.gstatic.com/faviconV2?client=SOCIAL&type=FAVICON&fallback_opts=TYPE,SIZE,URL&url=https://allclassic.porn&size=48",
        "apiVersion": 1,
        "repositoryUrl": "https://github.com/Kraptor123/Cs-GizliKeyif",
        "fileSize": 18306,
        "status": 1,
        "language": "en",
        "authors": [
            "kraptor"
        ],
        "tvTypes": [
            "NSFW"
        ],
        "version": 3,
        "internalName": "AllClassicPorn",
        "description": "Exclusive downloadable retro porn videos on AllClassic.porn. Full movies and best hardcore compilations from the old days. Hottest pornstars and antique homemade porn from all over the world.",
        "url": "https://raw.githubusercontent.com/Kraptor123/Cs-GizliKeyif/builds/AllClassicPorn.cs3",
        "name": "AllClassicPorn"
    },
    {
        "iconUrl": "https://t1.gstatic.com/faviconV2?client=SOCIAL&type=FAVICON&fallback_opts=TYPE,SIZE,URL&url=https://www.arabx.cam&size=128",
        "apiVersion": 1,
        "repositoryUrl": "https://github.com/Kraptor123/Cs-GizliKeyif",
        "fileSize": 22511,
        "status": 1,
        "language": "ar",
        "authors": [
            "kraptor"
        ],
        "tvTypes": [
            "NSFW"
        ],
        "version": 2,
        "internalName": "ArabX",
        "description": "\u0639\u0631\u0628 \u0627\u0643\u0633 | \u0633\u0643\u0633 \u0645\u062a\u0631\u062c\u0645 \u0627\u0643\u0628\u0631 \u0645\u0648\u0642\u0639 \u0627\u0641\u0644\u0627\u0645 \u0633\u0643\u0633 \u0627\u0644\u0639\u0631\u0628 \u0645\u062a\u0631\u062c\u0645 \u0644\u0627\u0641\u0644\u0627\u0645 \u0627\u0644\u0633\u0643\u0633 \u0627\u0644\u0645\u062a\u0631\u062c\u0645 \u0628\u0627\u062d\u062a\u0631\u0627\u0641\u064a\u0647 \u0639\u0627\u0644\u064a\u0629 \u0648\u0645\u0642\u0627\u0637\u0639 \u0627\u0644\u0627\u0641\u0644\u0627\u0645 \u0627\u0644\u062c\u0646\u0633\u064a\u0629 \u0627\u0644\u062c\u062f\u064a\u062f\u0629 \u0627\u0644\u062a\u064a \u062a\u0631\u0636\u064a \u0630\u0648\u0642\u0643 , \u0633\u0643\u0633 \u0627\u0645\u0647\u0627\u062a , \u0633\u0643\u0633 \u0645\u062d\u0627\u0631\u0645 , \u0627\u0641\u0644\u0627\u0645 \u0633\u0643\u0633 , \u0627\u0641\u0644\u0627\u0645 \u062c\u0646\u0633\u064a\u0647 , \u0627\u0641\u0644\u0627\u0645 \u0633\u0643\u0633 \u0646\u064a\u0643 \u0645\u062a\u0631\u062c\u0645\u0647 , \u0633\u0643\u0633 \u0645\u062a\u0631\u062c\u0645 \u0639\u0631\u0628\u064a - \u0646\u064a\u0643 \u0645\u062d\u0627\u0631\u0645 \u0645\u062a\u0631\u062c\u0645 - \u0645\u0648\u0642\u0639 \u0639\u0631\u0628 \u0627\u0643\u0633.",
        "url": "https://raw.githubusercontent.com/Kraptor123/Cs-GizliKeyif/builds/ArabX.cs3",
        "name": "ArabX"
    },
    {
        "iconUrl": "https://t3.gstatic.com/faviconV2?client=SOCIAL&type=FAVICON&fallback_opts=TYPE,SIZE,URL&url=https://www.arbada.com/&size=128",
        "apiVersion": 1,
        "repositoryUrl": "https://github.com/Kraptor123/Cs-GizliKeyif",
        "fileSize": 13270,
        "status": 1,
        "language": "ar",
        "authors": [
            "kraptor"
        ],
        "tvTypes": [
            "NSFW"
        ],
        "version": 1,
        "internalName": "Arbada",
        "description": "\u0633\u0643\u0633 \u0639\u0631\u0628\u062f\u0629 \u0647\u0648 \u0623\u0642\u0648\u0649 \u0645\u0648\u0642\u0639 \u0623\u0641\u0644\u0627\u0645 \u0648\u0635\u0648\u0631 \u0648\u0645\u0642\u0627\u0637\u0639 \u0648\u0642\u0635\u0635 \u0625\u0628\u0627\u062d\u064a\u0629 \u0639\u0644\u0649 \u0627\u0644\u0633\u0627\u062d\u0629 \u0627\u0644\u0639\u0631\u0628\u064a\u0629",
        "url": "https://raw.githubusercontent.com/Kraptor123/Cs-GizliKeyif/builds/Arbada.cs3",
        "name": "Arbada"
    },
    {
        "iconUrl": "https://t0.gstatic.com/faviconV2?client=SOCIAL&type=FAVICON&fallback_opts=TYPE,SIZE,URL&url=https://www.aznude.com/&size=48",
        "apiVersion": 1,
        "repositoryUrl": "https://github.com/Kraptor123/Cs-GizliKeyif",
        "fileSize": 23546,
        "status": 1,
        "language": "en",
        "authors": [
            "kraptor"
        ],
        "tvTypes": [
            "NSFW"
        ],
        "version": 7,
        "internalName": "AZNude",
        "description": "Welcome to AZNUDE! We have a large, free, every day growing universe of celebrity nudity where stars from all movies and series shine.",
        "url": "https://raw.githubusercontent.com/Kraptor123/Cs-GizliKeyif/builds/AZNude.cs3",
        "name": "AZNude"
    },
    {
        "iconUrl": "https://www.google.com/s2/favicons?domain=https://www.badtv.net/&sz=%size%",
        "apiVersion": 1,
        "repositoryUrl": "https://github.com/Kraptor123/Cs-GizliKeyif",
        "fileSize": 15653,
        "status": 1,
        "language": "tr",
        "authors": [
            "kerimmkirac"
        ],
        "tvTypes": [
            "NSFW"
        ],
        "version": 3,
        "internalName": "BadTv",
        "description": "Porno film izle \u2b50 \u2764\ufe0f \u2b50 HD porn DoEda canl\u0131 siki\u015f konulu sex video XXX altyaz\u0131l\u0131 porna \u26a1 mobil tecav\u00fcz pornosu \u2757 T\u00fcrk seks g\u00f6r\u00fcnt\u00fcleri seyret, pornolar.",
        "url": "https://raw.githubusercontent.com/Kraptor123/Cs-GizliKeyif/builds/BadTv.cs3",
        "name": "BadTv"
    },
    {
        "iconUrl": "https://t1.gstatic.com/faviconV2?client=SOCIAL&type=FAVICON&fallback_opts=TYPE,SIZE,URL&url=https://beeg.com/&size=128",
        "apiVersion": 1,
        "repositoryUrl": "https://github.com/Kraptor123/Cs-GizliKeyif",
        "fileSize": 17819,
        "status": 1,
        "language": "en",
        "authors": [
            "kraptor"
        ],
        "tvTypes": [
            "NSFW"
        ],
        "version": 3,
        "internalName": "Beeg",
        "description": "Beeg.com is a free porn website that features a wide variety of adult videos. It has a large selection of videos from various genres.",
        "url": "https://raw.githubusercontent.com/Kraptor123/Cs-GizliKeyif/builds/Beeg.cs3",
        "name": "Beeg"
    },
    {
        "iconUrl": "https://camwh.com/contents/ugmtofwqltgh/theme/logo.png",
        "apiVersion": 1,
        "repositoryUrl": "https://github.com/Kraptor123/Cs-GizliKeyif",
        "fileSize": 10633,
        "status": 1,
        "language": "en",
        "authors": [
            "kerimmkirac"
        ],
        "tvTypes": [
            "NSFW"
        ],
        "version": 3,
        "internalName": "CamWh",
        "description": "Free Videos to Watch, Hottest Moments, Private Show, Best Clips, Sexy Webcam Girls, Cam Whores Archive",
        "url": "https://raw.githubusercontent.com/Kraptor123/Cs-GizliKeyif/builds/CamWh.cs3",
        "name": "CamWh"
    },
    {
        "iconUrl": "https://web.static.mmcdn.com/favicons/apple-touch-icon-120x120.png?hash=b494063e083a",
        "apiVersion": 1,
        "repositoryUrl": "https://github.com/Kraptor123/Cs-GizliKeyif",
        "fileSize": 12897,
        "status": 1,
        "language": "en",
        "authors": [
            "kraptor",
            "luck731"
        ],
        "tvTypes": [
            "NSFW"
        ],
        "version": 2,
        "internalName": "Chatrubate",
        "description": "Chaturbate - Free Adult Webcams, Live Sex, Free Sex Chat, Exhibitionist & Pornstar Free Cams",
        "url": "https://raw.githubusercontent.com/Kraptor123/Cs-GizliKeyif/builds/Chatrubate.cs3",
        "name": "Chatrubate"
    },
    {
        "iconUrl": "https://www.google.com/s2/favicons?domain=collectionofbestporn.com&sz=%size%",
        "apiVersion": 1,
        "repositoryUrl": "https://github.com/Kraptor123/Cs-GizliKeyif",
        "fileSize": 13034,
        "status": 1,
        "language": "en",
        "authors": [
            "kerimmkirac"
        ],
        "tvTypes": [
            "NSFW"
        ],
        "version": 3,
        "internalName": "CollectionOfBestPorn",
        "description": "Watch the biggest collection of the best free high quality hd porn videos. There are over 1.5 million of the best porno tube movies completely FREE for you!",
        "url": "https://raw.githubusercontent.com/Kraptor123/Cs-GizliKeyif/builds/CollectionOfBestPorn.cs3",
        "name": "CollectionOfBestPorn"
    },
    {
        "iconUrl": "https://t3.gstatic.com/faviconV2?client=SOCIAL&type=FAVICON&fallback_opts=TYPE,SIZE,URL&url=http://coomer.st&size=32",
        "apiVersion": 1,
        "repositoryUrl": "https://github.com/Kraptor123/Cs-GizliKeyif",
        "fileSize": 45470,
        "status": 1,
        "language": "en",
        "authors": [
            "kraptor"
        ],
        "tvTypes": [
            "NSFW"
        ],
        "version": 12,
        "internalName": "Coomer",
        "description": "Coomer: supports photos and videos",
        "url": "https://raw.githubusercontent.com/Kraptor123/Cs-GizliKeyif/builds/Coomer.cs3",
        "name": "Coomer"
    },
    {
        "iconUrl": "https://cosxplay.com/storage/2020/08/cropped-favicon-cosxplay-32x32.png",
        "apiVersion": 1,
        "repositoryUrl": "https://github.com/Kraptor123/Cs-GizliKeyif",
        "fileSize": 14248,
        "status": 1,
        "language": "en",
        "authors": [
            "kraptor"
        ],
        "tvTypes": [
            "NSFW"
        ],
        "version": 1,
        "internalName": "CosXPlay",
        "description": "Free Cosplay porn videos \u2764\ufe0f! Beautiful girls clothed as your favorite characters from video games, TV shows and movies. Cosplay porn ONLY!",
        "url": "https://raw.githubusercontent.com/Kraptor123/Cs-GizliKeyif/builds/CosXPlay.cs3",
        "name": "CosXPlay"
    },
    {
        "iconUrl": "http://www.google.com/s2/favicons?domain=cumlouder.com",
        "apiVersion": 1,
        "repositoryUrl": "https://github.com/Kraptor123/Cs-GizliKeyif",
        "fileSize": 12891,
        "status": 1,
        "language": "en",
        "authors": [
            "ByAyzen, Kraptor"
        ],
        "tvTypes": [
            "NSFW"
        ],
        "version": 2,
        "internalName": "Cumlouder",
        "description": "Cumlouder, Internet is for porn!",
        "url": "https://raw.githubusercontent.com/Kraptor123/Cs-GizliKeyif/builds/Cumlouder.cs3",
        "name": "Cumlouder"
    },
    {
        "iconUrl": "https://t3.gstatic.com/faviconV2?client=SOCIAL&type=FAVICON&fallback_opts=TYPE,SIZE,URL&url=https://dirtyship.com&size=48",
        "apiVersion": 1,
        "repositoryUrl": "https://github.com/Kraptor123/Cs-GizliKeyif",
        "fileSize": 26666,
        "status": 1,
        "language": "en",
        "authors": [
            "kraptor"
        ],
        "tvTypes": [
            "NSFW"
        ],
        "version": 8,
        "internalName": "DirtyShip",
        "description": "Dirtyship.com is the hub of daily free leaked nudes from the hottest female Twitch, Snapchat, YouTube, Instagram, Patreon models, Cosplay, Gamer Girls, and streamers. Choose from the biggest selection of Sexy Leaked Nude Photos, Accidental Slips, Bikini Photos, Banned Streamers and Patreon Creators.",
        "url": "https://raw.githubusercontent.com/Kraptor123/Cs-GizliKeyif/builds/DirtyShip.cs3",
        "name": "DirtyShip"
    },
    {
        "iconUrl": "https://t0.gstatic.com/faviconV2?client=SOCIAL&type=FAVICON&fallback_opts=TYPE,SIZE,URL&url=https://www.doeda.one/&size=48",
        "apiVersion": 1,
        "repositoryUrl": "https://github.com/Kraptor123/Cs-GizliKeyif",
        "fileSize": 17829,
        "status": 1,
        "language": "tr",
        "authors": [
            "kraptor"
        ],
        "tvTypes": [
            "NSFW"
        ],
        "version": 6,
        "internalName": "Doeda",
        "description": "Porno izle T\u00fcrk \u2764 Porn sex video \u2618 Doeda inan\u0131lmaz Amat\u00f6r porna ve siki\u015f filmleri seyret \u2b50 altyaz\u0131l\u0131 Full HD pornosu \u2b50 endi\u015fe verici T\u00fcrk\u00e7e dublaj pornolar.",
        "url": "https://raw.githubusercontent.com/Kraptor123/Cs-GizliKeyif/builds/Doeda.cs3",
        "name": "Doeda"
    },
    {
        "iconUrl": "https://www.google.com/s2/favicons?domain=www.doeda.com&sz=%size%",
        "apiVersion": 1,
        "repositoryUrl": "https://github.com/Kraptor123/Cs-GizliKeyif",
        "fileSize": 15531,
        "status": 1,
        "language": "tr",
        "authors": [
            "kerimmkirac"
        ],
        "tvTypes": [
            "NSFW"
        ],
        "version": 5,
        "internalName": "DoedaOrijinal",
        "description": "Porno film izle \u2764\ufe0f bedava seks filmi seyret \u2764\ufe0f g\u00f6tten siki\u015f, pornu \u2b50 mobil porno limitsiz \u2b50 Tecav\u00fcz porna hd yeni Rokettube, h\u0131zl\u0131 DoEda \u00fccretsiz sex porn.",
        "url": "https://raw.githubusercontent.com/Kraptor123/Cs-GizliKeyif/builds/DoedaOrijinal.cs3",
        "name": "DoedaOrijinal"
    },
    {
        "iconUrl": "https://www.google.com/s2/favicons?domain=www.creativewoodtrade.com&sz=%size%",
        "apiVersion": 1,
        "repositoryUrl": "https://github.com/Kraptor123/Cs-GizliKeyif",
        "fileSize": 15373,
        "status": 1,
        "language": "tr",
        "authors": [
            "kerimmkirac"
        ],
        "tvTypes": [
            "NSFW"
        ],
        "version": 8,
        "internalName": "Domlepen",
        "description": "Porno videolar\u0131n\u0131 tak\u0131lma ve donma olmadan bedava, hd kalitede kesintisiz izle. Her g\u00fcn eklenen en yeni, en kaliteli porno filmlerinin keyfini \u00e7\u0131kart.",
        "url": "https://raw.githubusercontent.com/Kraptor123/Cs-GizliKeyif/builds/Domlepen.cs3",
        "name": "Domlepen"
    },
    {
        "iconUrl": "https://t0.gstatic.com/faviconV2?client=SOCIAL&type=FAVICON&fallback_opts=TYPE,SIZE,URL&url=https://efukt.com/&size=16",
        "apiVersion": 1,
        "repositoryUrl": "https://github.com/Kraptor123/Cs-GizliKeyif",
        "fileSize": 14843,
        "status": 1,
        "language": "en",
        "authors": [
            "kraptor"
        ],
        "tvTypes": [
            "NSFW"
        ],
        "version": 4,
        "internalName": "EFukt",
        "description": "Adult humor for adults, Makers of Lulz. Shocking Humor, Porn bloopers, Porn Fails, Cam Whores, Amateur Porn and more.",
        "url": "https://raw.githubusercontent.com/Kraptor123/Cs-GizliKeyif/builds/EFukt.cs3",
        "name": "EFukt"
    },
    {
        "iconUrl": "https://t0.gstatic.com/faviconV2?client=SOCIAL&type=FAVICON&fallback_opts=TYPE,SIZE,URL&url=https://epawg.com/&size=32",
        "apiVersion": 1,
        "repositoryUrl": "https://github.com/Kraptor123/Cs-GizliKeyif",
        "fileSize": 17588,
        "status": 1,
        "language": "en",
        "authors": [
            "kraptor"
        ],
        "tvTypes": [
            "NSFW"
        ],
        "version": 3,
        "internalName": "ePawg",
        "description": "Enjoy a huge selection of custom porn videos starring sexy amateur models from OnlyFans and Snapchat. Real girls posting sex videos in dozens of categories!",
        "url": "https://raw.githubusercontent.com/Kraptor123/Cs-GizliKeyif/builds/ePawg.cs3",
        "name": "ePawg"
    },
    {
        "iconUrl": "https://t0.gstatic.com/faviconV2?client=SOCIAL&type=FAVICON&fallback_opts=TYPE,SIZE,URL&url=https://www.eporner.com/&size=128",
        "apiVersion": 1,
        "repositoryUrl": "https://github.com/Kraptor123/Cs-GizliKeyif",
        "fileSize": 13874,
        "status": 1,
        "language": "en",
        "authors": [
            "ByAyzen"
        ],
        "tvTypes": [
            "NSFW"
        ],
        "version": 3,
        "internalName": "EPorner",
        "description": "Watch Full HD Porn Videos for free. We have over 4,975,164 full length Hardcore HD Sex Movies in 720p, 1080p and 4K that you can watch online or download.",
        "url": "https://raw.githubusercontent.com/Kraptor123/Cs-GizliKeyif/builds/EPorner.cs3",
        "name": "EPorner"
    },
    {
        "iconUrl": "https://t0.gstatic.com/faviconV2?client=SOCIAL&type=FAVICON&fallback_opts=TYPE,SIZE,URL&url=http://erome.com&size=128",
        "apiVersion": 1,
        "repositoryUrl": "https://github.com/Kraptor123/Cs-GizliKeyif",
        "fileSize": 15345,
        "status": 1,
        "language": "en",
        "authors": [
            "ByAyzen"
        ],
        "tvTypes": [
            "NSFW"
        ],
        "version": 2,
        "internalName": "Erome",
        "description": "Erome.com is a hosting platform that provides a safe and easy way to upload, store and share all your wild & erotic photos & videos. You control who you share your stuff with.",
        "url": "https://raw.githubusercontent.com/Kraptor123/Cs-GizliKeyif/builds/Erome.cs3",
        "name": "Erome"
    },
    {
        "iconUrl": "https://t2.gstatic.com/faviconV2?client=SOCIAL&type=FAVICON&fallback_opts=TYPE,SIZE,URL&url=https://erothots.is/&size=128",
        "apiVersion": 1,
        "repositoryUrl": "https://github.com/Kraptor123/Cs-GizliKeyif",
        "fileSize": 13176,
        "status": 1,
        "language": "en",
        "authors": [
            "kraptor"
        ],
        "tvTypes": [
            "NSFW"
        ],
        "version": 2,
        "internalName": "EroThots",
        "description": "Erothots Huge Free Place To Find Leaked onlyfans models Videos And images, Models, Pornstars, Gifs ...",
        "url": "https://raw.githubusercontent.com/Kraptor123/Cs-GizliKeyif/builds/EroThots.cs3",
        "name": "EroThots"
    },
    {
        "iconUrl": "https://www.google.com/s2/favicons?domain=www.evooli.com&sz=%size%",
        "apiVersion": 1,
        "repositoryUrl": "https://github.com/Kraptor123/Cs-GizliKeyif",
        "fileSize": 12956,
        "status": 1,
        "language": "tr",
        "authors": [
            "kerimmkirac"
        ],
        "tvTypes": [
            "NSFW"
        ],
        "version": 3,
        "internalName": "Evooli",
        "description": "Porno keyfini Evooli ile daha iyi \u00e7\u0131kart\u0131p hazz\u0131 doruklarda ya\u015famaya haz\u0131rsan, hadi durma HD Porno Filmlerini \u00fccretsiz izle.",
        "url": "https://raw.githubusercontent.com/Kraptor123/Cs-GizliKeyif/builds/Evooli.cs3",
        "name": "Evooli"
    },
    {
        "iconUrl": "https://www.google.com/s2/favicons?domain=familypornhd.com&sz=%size%",
        "apiVersion": 1,
        "repositoryUrl": "https://github.com/Kraptor123/Cs-GizliKeyif",
        "fileSize": 15683,
        "status": 1,
        "language": "en",
        "authors": [
            "kraptor",
            "kerimmkirac"
        ],
        "tvTypes": [
            "NSFW"
        ],
        "version": 6,
        "internalName": "FamilyPorn",
        "description": "FamilyPornHD It's a natural mix of the neighborhood stepmoms, older stepdads, barely legal stepsisters, and even the college going stepbrother falling into some serious family fun.",
        "url": "https://raw.githubusercontent.com/Kraptor123/Cs-GizliKeyif/builds/FamilyPorn.cs3",
        "name": "FamilyPorn"
    },
    {
        "iconUrl": "https://fapix.porn/favicon.ico",
        "apiVersion": 1,
        "repositoryUrl": "https://github.com/Kraptor123/Cs-GizliKeyif",
        "fileSize": 11211,
        "status": 1,
        "language": "en",
        "authors": [
            "kerimmkirac"
        ],
        "tvTypes": [
            "NSFW"
        ],
        "version": 2,
        "internalName": "Fapix",
        "description": "The only one site where you can filter videos by 4 tags at once for free. We have a lot of great videos, we're sure you'll like them",
        "url": "https://raw.githubusercontent.com/Kraptor123/Cs-GizliKeyif/builds/Fapix.cs3",
        "name": "Fapix"
    },
    {
        "iconUrl": "https://www.google.com/s2/favicons?domain=www.freepornvideos.xxx&sz=%size%",
        "apiVersion": 1,
        "repositoryUrl": "https://github.com/Kraptor123/Cs-GizliKeyif",
        "fileSize": 13875,
        "status": 1,
        "language": "en",
        "authors": [
            "kerimmkirac"
        ],
        "tvTypes": [
            "NSFW"
        ],
        "version": 4,
        "internalName": "FreePornVideos",
        "description": "Check out \ud83d\udd25 Full Length Porn Videos from Top Studios in Ultra HD. NO annoying ADS \u2714",
        "url": "https://raw.githubusercontent.com/Kraptor123/Cs-GizliKeyif/builds/FreePornVideos.cs3",
        "name": "FreePornVideos"
    },
    {
        "iconUrl": "https://t1.gstatic.com/faviconV2?client=SOCIAL&type=FAVICON&fallback_opts=TYPE,SIZE,URL&url=https://www.freeuseporn.com&size=128",
        "apiVersion": 1,
        "repositoryUrl": "https://github.com/Kraptor123/Cs-GizliKeyif",
        "fileSize": 10696,
        "status": 1,
        "language": "en",
        "authors": [
            "kraptor"
        ],
        "tvTypes": [
            "NSFW"
        ],
        "version": 1,
        "internalName": "FreeUsePorn",
        "description": "Watch High Quality Freeuse Porn Videos for free! Thousands of videos available for all freeuse porn categories including: Free Service Porn, Hypno Porn, Mind Control Porn, and more! Join our community and unlock video downloads, custom favorite lists, and more!",
        "url": "https://raw.githubusercontent.com/Kraptor123/Cs-GizliKeyif/builds/FreeUsePorn.cs3",
        "name": "FreeUsePorn"
    },
    {
        "iconUrl": "https://freshporno.net/favicon.ico",
        "apiVersion": 1,
        "repositoryUrl": "https://github.com/Kraptor123/Cs-GizliKeyif",
        "fileSize": 11016,
        "status": 1,
        "language": "en",
        "authors": [
            "ByAyzen"
        ],
        "tvTypes": [
            "NSFW"
        ],
        "version": 1,
        "internalName": "Freshporno",
        "description": "Daily updated porn tube, with exclusive porn videos.",
        "url": "https://raw.githubusercontent.com/Kraptor123/Cs-GizliKeyif/builds/Freshporno.cs3",
        "name": "Freshporno"
    },
    {
        "iconUrl": "https://www.google.com/s2/favicons?domain=fullporner.com&sz=%size%",
        "apiVersion": 1,
        "repositoryUrl": "https://github.com/Kraptor123/Cs-GizliKeyif",
        "fileSize": 19168,
        "status": 1,
        "language": "en",
        "authors": [
            "kraptor"
        ],
        "tvTypes": [
            "NSFW"
        ],
        "version": 7,
        "internalName": "FullPorner",
        "description": "(VPN) FullPorner is the best free full length porn video site. Choose from millions of hardcore videos that stream quickly and in high quality and only full length",
        "url": "https://raw.githubusercontent.com/Kraptor123/Cs-GizliKeyif/builds/FullPorner.cs3",
        "name": "FullPorner"
    },
    {
        "iconUrl": "https://t2.gstatic.com/faviconV2?client=SOCIAL&type=FAVICON&fallback_opts=TYPE,SIZE,URL&url=https://fyptt.to/wp-content/uploads/2020/04/fypttlogo-white.png&size=128",
        "apiVersion": 1,
        "repositoryUrl": "https://github.com/Kraptor123/Cs-GizliKeyif",
        "fileSize": 11453,
        "status": 1,
        "language": "en",
        "authors": [
            "ByAyzen"
        ],
        "tvTypes": [
            "NSFW"
        ],
        "version": 1,
        "internalName": "Fyptt",
        "description": "If you think you can't find TikTok, Shorts, and Reels-inspired porn videos then FYPTT will prove you wrong. Here on our site, you can find lots of adult TikTok-, Shorts-, and Reels-like vertical porn videos that are hard to find anywhere else. You'll see familiar challenges, but they're all NSFW and contain nudity. Feel turned on? Start browsing FYPTT right now and remember to come back regularly because we update content very often.",
        "url": "https://raw.githubusercontent.com/Kraptor123/Cs-GizliKeyif/builds/Fyptt.cs3",
        "name": "Fyptt"
    },
    {
        "iconUrl": "https://www.google.com/s2/favicons?domain=hdabla.net&sz=%size%",
        "apiVersion": 1,
        "repositoryUrl": "https://github.com/Kraptor123/Cs-GizliKeyif",
        "fileSize": 14265,
        "status": 1,
        "language": "tr",
        "authors": [
            "kerimmkirac"
        ],
        "tvTypes": [
            "NSFW"
        ],
        "version": 2,
        "internalName": "HdAbla",
        "description": "Porno film izlemek i\u00e7in HdAbla sitesini ziyaret edin. Keyifle mobil siki\u015f seyret. Sex ve rokettube seks videolar\u0131n\u0131 g\u00fcncel olarak Full HD kalitede bedava adult porn sunuyoruz",
        "url": "https://raw.githubusercontent.com/Kraptor123/Cs-GizliKeyif/builds/HdAbla.cs3",
        "name": "HdAbla"
    },
    {
        "iconUrl": "https://www.google.com/s2/favicons?sz=48&domain=https://hdstream.ing",
        "apiVersion": 1,
        "repositoryUrl": "https://github.com/Kraptor123/Cs-GizliKeyif",
        "fileSize": 10663,
        "status": 1,
        "language": "en",
        "authors": [
            "kraptor"
        ],
        "tvTypes": [
            "NSFW"
        ],
        "version": 2,
        "internalName": "HDStreaming",
        "description": "Free Recorded Stripchat Cams! No Registration Required. Review old streams with amateurs, in HD Video.",
        "url": "https://raw.githubusercontent.com/Kraptor123/Cs-GizliKeyif/builds/HDStreaming.cs3",
        "name": "HDStreaming"
    },
    {
        "iconUrl": "https://t0.gstatic.com/faviconV2?client=SOCIAL&type=FAVICON&fallback_opts=TYPE,SIZE,URL&url=http://hentaila.tv&size=128",
        "apiVersion": 1,
        "repositoryUrl": "https://github.com/Kraptor123/Cs-GizliKeyif",
        "fileSize": 25885,
        "status": 1,
        "language": "mx",
        "authors": [
            "ByAyzen"
        ],
        "tvTypes": [
            "NSFW"
        ],
        "version": 1,
        "internalName": "Hentaila",
        "description": "porn",
        "url": "https://raw.githubusercontent.com/Kraptor123/Cs-GizliKeyif/builds/Hentaila.cs3",
        "name": "Hentaila"
    },
    {
        "iconUrl": "https://t0.gstatic.com/faviconV2?client=SOCIAL&type=FAVICON&fallback_opts=TYPE,SIZE,URL&url=https://hentaiworld.tv/&size=128",
        "apiVersion": 1,
        "repositoryUrl": "https://github.com/Kraptor123/Cs-GizliKeyif",
        "fileSize": 13532,
        "status": 1,
        "language": "en",
        "authors": [
            "ByAyzen"
        ],
        "tvTypes": [
            "NSFW"
        ],
        "version": 1,
        "internalName": "HentaiWorld",
        "description": "Watch high quality hentai videos streamed online in 720p and 1080p - HentaiWorld. Find your favorite hentai videos. Watch the best hentai videos on HentaiWorld.",
        "url": "https://raw.githubusercontent.com/Kraptor123/Cs-GizliKeyif/builds/HentaiWorld.cs3",
        "name": "HentaiWorld"
    },
    {
        "iconUrl": "https://t2.gstatic.com/faviconV2?client=SOCIAL&type=FAVICON&fallback_opts=TYPE,SIZE,URL&url=https://www.hentaizm6.online/core/views/086f35f924/fav.ico&size=64",
        "apiVersion": 1,
        "repositoryUrl": "https://github.com/Kraptor123/Cs-GizliKeyif",
        "fileSize": 26125,
        "status": 1,
        "language": "tr",
        "authors": [
            "kraptor"
        ],
        "tvTypes": [
            "NSFW"
        ],
        "version": 10,
        "internalName": "Hentaizm",
        "description": "hentaizm, t\u00fcrk\u00e7e altyaz\u0131l\u0131 hentai izle.",
        "url": "https://raw.githubusercontent.com/Kraptor123/Cs-GizliKeyif/builds/Hentaizm.cs3",
        "name": "Hentaizm"
    },
    {
        "iconUrl": "https://t3.gstatic.com/faviconV2?client=SOCIAL&type=FAVICON&fallback_opts=TYPE,SIZE,URL&url=https://manga.hentaizm6.online/&size=64",
        "apiVersion": 1,
        "repositoryUrl": "https://github.com/Kraptor123/Cs-GizliKeyif",
        "fileSize": 26067,
        "status": 1,
        "language": "tr",
        "authors": [
            "kraptor"
        ],
        "tvTypes": [
            "NSFW"
        ],
        "version": 3,
        "internalName": "HentaizmManga",
        "description": "[TEST A\u015eAMASINDA]Hentai Manga Oku, Yeti\u015fkin Webtoon Oku.",
        "url": "https://raw.githubusercontent.com/Kraptor123/Cs-GizliKeyif/builds/HentaizmManga.cs3",
        "name": "HentaizmManga"
    },
    {
        "iconUrl": "https://www.google.com/s2/favicons?domain=https://hotleak.vip/&sz=%size%",
        "apiVersion": 1,
        "repositoryUrl": "https://github.com/Kraptor123/Cs-GizliKeyif",
        "fileSize": 12825,
        "status": 1,
        "language": "en",
        "authors": [
            "kerimmkirac",
            "kraptor"
        ],
        "tvTypes": [
            "NSFW"
        ],
        "version": 4,
        "internalName": "HotLeak",
        "description": "Hotleak is the best free porn site of Millions Exclusive Leak contents such as Images, Gallery and Videos.",
        "url": "https://raw.githubusercontent.com/Kraptor123/Cs-GizliKeyif/builds/HotLeak.cs3",
        "name": "HotLeak"
    },
    {
        "iconUrl": "https://hqcollect.com/wp-content/uploads/2020/03/circle-logo.jpg",
        "apiVersion": 1,
        "repositoryUrl": "https://github.com/Kraptor123/Cs-GizliKeyif",
        "fileSize": 12403,
        "status": 1,
        "language": "en",
        "authors": [
            "kraptor"
        ],
        "tvTypes": [
            "NSFW"
        ],
        "version": 4,
        "internalName": "HQCollect",
        "description": "Watch the latest hardcore XXX porn videos of FacialAbuse, GhettoGaggers, LatinaAbuse, BlackPayback and RadicalJizzlam",
        "url": "https://raw.githubusercontent.com/Kraptor123/Cs-GizliKeyif/builds/HQCollect.cs3",
        "name": "HQCollect"
    },
    {
        "iconUrl": "https://t0.gstatic.com/faviconV2?client=SOCIAL&type=FAVICON&fallback_opts=TYPE,SIZE,URL&url=https://hqporner.com/&size=32",
        "apiVersion": 1,
        "repositoryUrl": "https://github.com/Kraptor123/Cs-GizliKeyif",
        "fileSize": 14857,
        "status": 1,
        "language": "en",
        "authors": [
            "kraptor"
        ],
        "tvTypes": [
            "NSFW"
        ],
        "version": 2,
        "internalName": "HQPorner",
        "description": "Truly high definition porn videos and truly for free! We're sure you'll like our best collection containing thousands of 4K, 60FPS and 1080p free HD porn videos with the hottest girls ever!",
        "url": "https://raw.githubusercontent.com/Kraptor123/Cs-GizliKeyif/builds/HQPorner.cs3",
        "name": "HQPorner"
    },
    {
        "iconUrl": "https://turkifsaalemivip1.blog/wp-content/uploads/2025/10/cropped-yeni-logo-anasite-180x180.png",
        "apiVersion": 1,
        "repositoryUrl": "https://github.com/Kraptor123/Cs-GizliKeyif",
        "fileSize": 12076,
        "status": 1,
        "language": "tr",
        "authors": [
            "kraptor"
        ],
        "tvTypes": [
            "NSFW"
        ],
        "version": 4,
        "internalName": "IfsaLog",
        "description": "\u0130fsalog Saklanan ne varsa burada if\u015fa olur ! - T\u00fcrkiye\u2019nin en g\u00fcncel if\u015fa i\u00e7eriklerini HD kalitede ke\u015ffedin \u2013 s\u0131zd\u0131r\u0131lm\u0131\u015f videolar, \u00f6zel \u00e7ekimler ve sosyal medya medyas\u0131yla ger\u00e7ek if\u015falar \u015fimdi burada!",
        "url": "https://raw.githubusercontent.com/Kraptor123/Cs-GizliKeyif/builds/IfsaLog.cs3",
        "name": "IfsaLog"
    },
    {
        "iconUrl": "https://www.google.com/s2/favicons?domain=influencerchicks.com&sz=%size%",
        "apiVersion": 1,
        "repositoryUrl": "https://github.com/Kraptor123/Cs-GizliKeyif",
        "fileSize": 12233,
        "status": 1,
        "language": "en",
        "authors": [
            "kerimmkirac"
        ],
        "tvTypes": [
            "NSFW"
        ],
        "version": 4,
        "internalName": "\u0130nfluencerChicks",
        "description": "Daily updated nude influencer videos and photos for free only on InfluencerChicks.",
        "url": "https://raw.githubusercontent.com/Kraptor123/Cs-GizliKeyif/builds/\u0130nfluencerChicks.cs3",
        "name": "\u0130nfluencerChicks"
    },
    {
        "iconUrl": "https://www.google.com/s2/favicons?domain=jav.guru&sz=%size%",
        "apiVersion": 1,
        "repositoryUrl": "https://github.com/Kraptor123/Cs-GizliKeyif",
        "fileSize": 27316,
        "status": 1,
        "language": "jp",
        "authors": [
            "kraptor",
            "ByAyzen"
        ],
        "tvTypes": [
            "NSFW"
        ],
        "version": 7,
        "internalName": "JavGuru",
        "description": "JavGuru",
        "url": "https://raw.githubusercontent.com/Kraptor123/Cs-GizliKeyif/builds/JavGuru.cs3",
        "name": "JavGuru"
    },
    {
        "iconUrl": "https://javseen.tv/favicon-96x96.png",
        "apiVersion": 1,
        "repositoryUrl": "https://github.com/Kraptor123/Cs-GizliKeyif",
        "fileSize": 24499,
        "status": 1,
        "language": "jp",
        "authors": [
            "byayzen"
        ],
        "tvTypes": [
            "NSFW"
        ],
        "version": 1,
        "internalName": "Javseen",
        "description": "Watch Free JAV Sex Movies Streaming, Japanese Adult Videos, Tons of hot jav censored,Japanese tube, Japanese sex online.",
        "url": "https://raw.githubusercontent.com/Kraptor123/Cs-GizliKeyif/builds/Javseen.cs3",
        "name": "Javseen"
    },
    {
        "iconUrl": "https://www.google.com/s2/favicons?domain=www.kalite18.net&sz=%size%",
        "apiVersion": 1,
        "repositoryUrl": "https://github.com/Kraptor123/Cs-GizliKeyif",
        "fileSize": 13150,
        "status": 1,
        "language": "tr",
        "authors": [
            "kerimmkirac"
        ],
        "tvTypes": [
            "NSFW"
        ],
        "version": 2,
        "internalName": "Kalite18",
        "description": "Kalite18, sizlere porno filmleri HD kalite ve t\u00fcrk\u00e7e altyaz\u0131l\u0131 olarak izleme keyfi sunmaktad\u0131r. Porno ve sex filmlerini anlayarak 31 \u00e7ekmenin keyfini \u00e7\u0131kar\u0131n.",
        "url": "https://raw.githubusercontent.com/Kraptor123/Cs-GizliKeyif/builds/Kalite18.cs3",
        "name": "Kalite18"
    },
    {
        "iconUrl": "https://www.google.com/s2/favicons?domain=www.kopeda.com&sz=%size%",
        "apiVersion": 1,
        "repositoryUrl": "https://github.com/Kraptor123/Cs-GizliKeyif",
        "fileSize": 11292,
        "status": 1,
        "language": "tr",
        "authors": [
            "kerimmkirac"
        ],
        "tvTypes": [
            "NSFW"
        ],
        "version": 2,
        "internalName": "Kopeda",
        "description": "En kaliteli porno ve siki\u015f video sitesi olarak bak\u0131\u015f a\u00e7\u0131n\u0131z\u0131 de\u011fi\u015ftirmeye geldik. Premium pornolar\u0131 \u00fccretsiz olarak izlemek i\u00e7in t\u0131kla!",
        "url": "https://raw.githubusercontent.com/Kraptor123/Cs-GizliKeyif/builds/Kopeda.cs3",
        "name": "Kopeda"
    },
    {
        "iconUrl": "https://koreanpornmovie.com/wp-content/uploads/2020/01/cropped-koreanpornmovie-favicon-180x180.png",
        "apiVersion": 1,
        "repositoryUrl": "https://github.com/Kraptor123/Cs-GizliKeyif",
        "fileSize": 12384,
        "status": 1,
        "language": "tr",
        "authors": [
            "ByAyzen"
        ],
        "tvTypes": [
            "NSFW"
        ],
        "version": 3,
        "internalName": "Koreanpornmovie",
        "description": "KoreanPornMovie.com is a dedicated platform for fans of Korean adult films, offering a comprehensive collection of movies and clips from classic hits to the latest releases. Each title is carefully organized by genre, year, and performer, making it easy for visitors to find exactly what they are looking for.",
        "url": "https://raw.githubusercontent.com/Kraptor123/Cs-GizliKeyif/builds/Koreanpornmovie.cs3",
        "name": "Koreanpornmovie"
    },
    {
        "iconUrl": "https://www.google.com/s2/favicons?domain=koreaye.com&sz=%size%",
        "apiVersion": 1,
        "repositoryUrl": "https://github.com/Kraptor123/Cs-GizliKeyif",
        "fileSize": 11993,
        "status": 1,
        "language": "tr",
        "authors": [
            "kerimmkirac"
        ],
        "tvTypes": [
            "NSFW"
        ],
        "version": 3,
        "internalName": "Koreaye",
        "description": "Porno Film - Siki\u015f izle - Sex Video - Mobil Seks Seyret | Koreaye",
        "url": "https://raw.githubusercontent.com/Kraptor123/Cs-GizliKeyif/builds/Koreaye.cs3",
        "name": "Koreaye"
    },
    {
        "iconUrl": "https://t3.gstatic.com/faviconV2?client=SOCIAL&type=FAVICON&fallback_opts=TYPE,SIZE,URL&url=https://livecamrips.to&size=128",
        "apiVersion": 1,
        "repositoryUrl": "https://github.com/Kraptor123/Cs-GizliKeyif",
        "fileSize": 27216,
        "status": 1,
        "language": "en",
        "authors": [
            "kraptor",
            "kerimmkirac"
        ],
        "tvTypes": [
            "NSFW"
        ],
        "version": 13,
        "internalName": "LiveCamRips",
        "description": "LiveCamRips",
        "url": "https://raw.githubusercontent.com/Kraptor123/Cs-GizliKeyif/builds/LiveCamRips.cs3",
        "name": "LiveCamRips"
    },
    {
        "iconUrl": "https://www.google.com/s2/favicons?domain=maheir.com&sz=%size%",
        "apiVersion": 1,
        "repositoryUrl": "https://github.com/Kraptor123/Cs-GizliKeyif",
        "fileSize": 14350,
        "status": 1,
        "language": "tr",
        "authors": [
            "kerimmkirac"
        ],
        "tvTypes": [
            "NSFW"
        ],
        "version": 1,
        "internalName": "Maheir",
        "description": "Bo\u015falmak istedi\u011finiz zaman \u2764\ufe0f porno izle videolar\u0131na girebilir \u2764\ufe0f siki\u015f seyret keyfini ya\u015fay\u0131n. Konulu hd porn seksleriyle \u2b50 mobil porna filmi \u00e7ok daha g\u00fczel",
        "url": "https://raw.githubusercontent.com/Kraptor123/Cs-GizliKeyif/builds/Maheir.cs3",
        "name": "Maheir"
    },
    {
        "iconUrl": "https://mangoporn.net/wp-content/uploads/2024/07/mangoporn.net_.png",
        "apiVersion": 1,
        "repositoryUrl": "https://github.com/Kraptor123/Cs-GizliKeyif",
        "fileSize": 56330,
        "status": 1,
        "language": "en",
        "authors": [
            "kraptor",
            "ByAyzen",
            "HindiProvider"
        ],
        "tvTypes": [
            "NSFW"
        ],
        "version": 13,
        "internalName": "Mangoporn",
        "description": "MangoPorn",
        "url": "https://raw.githubusercontent.com/Kraptor123/Cs-GizliKeyif/builds/Mangoporn.cs3",
        "name": "Mangoporn"
    },
    {
        "iconUrl": "https://t3.gstatic.com/faviconV2?client=SOCIAL&type=FAVICON&fallback_opts=TYPE,SIZE,URL&url=https://milfnut.com&size=128",
        "apiVersion": 1,
        "repositoryUrl": "https://github.com/Kraptor123/Cs-GizliKeyif",
        "fileSize": 11947,
        "status": 1,
        "language": "en",
        "authors": [
            "kraptor"
        ],
        "tvTypes": [
            "NSFW"
        ],
        "version": 1,
        "internalName": "MilfNut",
        "description": "Milfnut provides free incest porn videos. Watch milf porn videos, mom son porn videos and other taboo porn on Milfnut.com.",
        "url": "https://raw.githubusercontent.com/Kraptor123/Cs-GizliKeyif/builds/MilfNut.cs3",
        "name": "MilfNut"
    },
    {
        "iconUrl": "https://missav.ws/missav/logo-square.png",
        "apiVersion": 1,
        "repositoryUrl": "https://github.com/Kraptor123/Cs-GizliKeyif",
        "fileSize": 11901,
        "status": 1,
        "language": "jp",
        "authors": [
            "ByAyzen"
        ],
        "tvTypes": [
            "NSFW"
        ],
        "version": 3,
        "internalName": "MissAV",
        "description": "Best Japan AV porn site, free forever, high speed, no lag, over 100,000 videos with daily update.",
        "url": "https://raw.githubusercontent.com/Kraptor123/Cs-GizliKeyif/builds/MissAV.cs3",
        "name": "MissAV"
    },
    {
        "iconUrl": "https://www.google.com/s2/favicons?domain=momlover.com&sz=%size%",
        "apiVersion": 1,
        "repositoryUrl": "https://github.com/Kraptor123/Cs-GizliKeyif",
        "fileSize": 11572,
        "status": 1,
        "language": "en",
        "authors": [
            "kerimmkirac"
        ],
        "tvTypes": [
            "NSFW"
        ],
        "version": 4,
        "internalName": "MomLover",
        "description": "The official all-exclusive MomLover Network featuring everything including: mom and her friends swapping sons, mom&rsquo;s delicious creampies, the tightest mom bodies...",
        "url": "https://raw.githubusercontent.com/Kraptor123/Cs-GizliKeyif/builds/MomLover.cs3",
        "name": "MomLover"
    },
    {
        "iconUrl": "https://t3.gstatic.com/faviconV2?client=SOCIAL&type=FAVICON&fallback_opts=TYPE,SIZE,URL&url=https://motherless.com/&size=16",
        "apiVersion": 1,
        "repositoryUrl": "https://github.com/Kraptor123/Cs-GizliKeyif",
        "fileSize": 16696,
        "status": 1,
        "language": "en",
        "authors": [
            "kraptor"
        ],
        "tvTypes": [
            "NSFW"
        ],
        "version": 8,
        "internalName": "Motherless",
        "description": "Motherless.com is a moral free file host where anything legal is hosted forever. Motherless has a very large and active community where you can meet like minded individuals.",
        "url": "https://raw.githubusercontent.com/Kraptor123/Cs-GizliKeyif/builds/Motherless.cs3",
        "name": "Motherless"
    },
    {
        "iconUrl": "https://www.google.com/s2/favicons?domain=netfapx.com&sz=%size%",
        "apiVersion": 1,
        "repositoryUrl": "https://github.com/Kraptor123/Cs-GizliKeyif",
        "fileSize": 14566,
        "status": 1,
        "language": "en",
        "authors": [
            "kerimmkirac"
        ],
        "tvTypes": [
            "NSFW"
        ],
        "version": 3,
        "internalName": "NetFapX",
        "description": "Watch HD porn sex videos for free. Large collection of tube porn videos in high quality. Very fast HD porn streaming. It's time to FAP!",
        "url": "https://raw.githubusercontent.com/Kraptor123/Cs-GizliKeyif/builds/NetFapX.cs3",
        "name": "NetFapX"
    },
    {
        "iconUrl": "https://noodlemagazine.com/static/extend/dark/apple-icon-120x120.png",
        "apiVersion": 1,
        "repositoryUrl": "https://github.com/Kraptor123/Cs-GizliKeyif",
        "fileSize": 13253,
        "status": 1,
        "language": "en",
        "authors": [
            "ByAyzen"
        ],
        "tvTypes": [
            "NSFW"
        ],
        "version": 2,
        "internalName": "NoodleMagazine",
        "description": "Biggest videos collection of high quality. Our entertainment portal finds the best video for you every day!",
        "url": "https://raw.githubusercontent.com/Kraptor123/Cs-GizliKeyif/builds/NoodleMagazine.cs3",
        "name": "NoodleMagazine"
    },
    {
        "iconUrl": "https://www.google.com/s2/favicons?domain=www.notmik.com&sz=%size%",
        "apiVersion": 1,
        "repositoryUrl": "https://github.com/Kraptor123/Cs-GizliKeyif",
        "fileSize": 12027,
        "status": 1,
        "language": "tr",
        "authors": [
            "kerimmkirac"
        ],
        "tvTypes": [
            "NSFW"
        ],
        "version": 2,
        "internalName": "Notmik",
        "description": "Porno sekt\u00f6r\u00fcn\u00fcn en g\u00fcncel porno izleme sitesi kar\u015f\u0131n\u0131zda. \u00dcnl\u00fc sitelerden eklenen premium pornolar\u0131 izlemek i\u00e7in hemen t\u0131kla!",
        "url": "https://raw.githubusercontent.com/Kraptor123/Cs-GizliKeyif/builds/Notmik.cs3",
        "name": "Notmik"
    },
    {
        "iconUrl": "https://www.google.com/s2/favicons?sz=128&domain=www.onscreens.me",
        "apiVersion": 1,
        "repositoryUrl": "https://github.com/Kraptor123/Cs-GizliKeyif",
        "fileSize": 20255,
        "status": 1,
        "language": "en",
        "authors": [
            "kraptor"
        ],
        "tvTypes": [
            "NSFW"
        ],
        "version": 1,
        "internalName": "OnScreens",
        "description": "Missed a show? OnScreens turns live cam broadcasts into an HD replay library from Chaturbate, Cam4, Stripchat, Bongacams &#38; more. Stream or download replays free.",
        "url": "https://raw.githubusercontent.com/Kraptor123/Cs-GizliKeyif/builds/OnScreens.cs3",
        "name": "OnScreens"
    },
    {
        "iconUrl": "https://www.google.com/s2/favicons?domain=www.perfectgirls.xxx&sz=%size%",
        "apiVersion": 1,
        "repositoryUrl": "https://github.com/Kraptor123/Cs-GizliKeyif",
        "fileSize": 13702,
        "status": 1,
        "language": "en",
        "authors": [
            "kerimmkirac"
        ],
        "tvTypes": [
            "NSFW"
        ],
        "version": 3,
        "internalName": "PerfectGirls",
        "description": "New free porn videos every day. Tons of adult movies in our archive. The only bookmark you need for all you free sex fantasies.",
        "url": "https://raw.githubusercontent.com/Kraptor123/Cs-GizliKeyif/builds/PerfectGirls.cs3",
        "name": "PerfectGirls"
    },
    {
        "iconUrl": "https://www.google.com/s2/favicons?domain=www.porn00.org&sz=%size%",
        "apiVersion": 1,
        "repositoryUrl": "https://github.com/Kraptor123/Cs-GizliKeyif",
        "fileSize": 19367,
        "status": 1,
        "language": "en",
        "authors": [
            "kraptor",
            "kerimmkirac"
        ],
        "tvTypes": [
            "NSFW"
        ],
        "version": 5,
        "internalName": "Porn00",
        "description": "Porn00 provides hd porn videos for fee. And we're offering latest 720p porn, xxx and sex videos at porn00.",
        "url": "https://raw.githubusercontent.com/Kraptor123/Cs-GizliKeyif/builds/Porn00.cs3",
        "name": "Porn00"
    },
    {
        "iconUrl": "https://t3.gstatic.com/faviconV2?client=SOCIAL&type=FAVICON&fallback_opts=TYPE,SIZE,URL&url=https://www.porn36.com&size=32",
        "apiVersion": 1,
        "repositoryUrl": "https://github.com/Kraptor123/Cs-GizliKeyif",
        "fileSize": 12065,
        "status": 1,
        "language": "en",
        "authors": [
            "kraptor"
        ],
        "tvTypes": [
            "NSFW"
        ],
        "version": 3,
        "internalName": "Porn36",
        "description": "Dive into a wild world of Porn Videos! Feast on free movies in spicy 4K & HD. Ads won\u2019t crash your party!",
        "url": "https://raw.githubusercontent.com/Kraptor123/Cs-GizliKeyif/builds/Porn36.cs3",
        "name": "Porn36"
    },
    {
        "iconUrl": "https://www.google.com/s2/favicons?domain=www.pornhat.com&sz=%size%",
        "apiVersion": 1,
        "repositoryUrl": "https://github.com/Kraptor123/Cs-GizliKeyif",
        "fileSize": 13753,
        "status": 1,
        "language": "en",
        "authors": [
            "kerimmkirac"
        ],
        "tvTypes": [
            "NSFW"
        ],
        "version": 3,
        "internalName": "PornHat",
        "description": "Watch new HD \u26a1 XXX movies at the Porn Hat tube for free! Famous pornstars \u2b50 and amateur girls \u270c\ufe0f. Stream it! Download it! Enjoy it!",
        "url": "https://raw.githubusercontent.com/Kraptor123/Cs-GizliKeyif/builds/PornHat.cs3",
        "name": "PornHat"
    },
    {
        "iconUrl": "https://t0.gstatic.com/faviconV2?client=SOCIAL&type=FAVICON&fallback_opts=TYPE,SIZE,URL&url=https://www.pornhub.com/&size=128",
        "apiVersion": 1,
        "repositoryUrl": "https://github.com/Kraptor123/Cs-GizliKeyif",
        "fileSize": 14603,
        "status": 1,
        "language": "en",
        "authors": [
            "kraptor"
        ],
        "tvTypes": [
            "NSFW"
        ],
        "version": 2,
        "internalName": "PornHub",
        "description": "Welcome to Pornhub.com, home of the best hardcore free porn videos with the hottest adult stars. Get full length scenes from your favorite porn studios 24/7!",
        "url": "https://raw.githubusercontent.com/Kraptor123/Cs-GizliKeyif/builds/PornHub.cs3",
        "name": "PornHub"
    },
    {
        "iconUrl": "https://www.google.com/s2/favicons?domain=pornoanne.com&sz=%size%",
        "apiVersion": 1,
        "repositoryUrl": "https://github.com/Kraptor123/Cs-GizliKeyif",
        "fileSize": 16060,
        "status": 1,
        "language": "tr",
        "authors": [
            "kraptor",
            "kerimmkirac"
        ],
        "tvTypes": [
            "NSFW"
        ],
        "version": 6,
        "internalName": "PornoAnne",
        "description": "Porno Anne ile en kaliteli HD porno filmleri burada! Sex videolar\u0131 ve siki\u015f sahneleri ile dolu anlara \u00fccretsiz porno izle yazarak ula\u015f ve siki\u015f seyret.",
        "url": "https://raw.githubusercontent.com/Kraptor123/Cs-GizliKeyif/builds/PornoAnne.cs3",
        "name": "PornoAnne"
    },
    {
        "iconUrl": "https://www.google.com/s2/favicons?domain=www.pornolandia.xxx&sz=%size%",
        "apiVersion": 1,
        "repositoryUrl": "https://github.com/Kraptor123/Cs-GizliKeyif",
        "fileSize": 10733,
        "status": 1,
        "language": "es",
        "authors": [
            "kerimmkirac"
        ],
        "tvTypes": [
            "NSFW"
        ],
        "version": 3,
        "internalName": "PornoLandia",
        "description": "Pornolandia \u00e9 o melhor site de videos porno gratis do Brasil. Encontre os melhores videos porn\u00f4 de mulheres gostosas, atualizados diariamente e com qualidade.",
        "url": "https://raw.githubusercontent.com/Kraptor123/Cs-GizliKeyif/builds/PornoLandia.cs3",
        "name": "PornoLandia"
    },
    {
        "iconUrl": "https://t2.gstatic.com/faviconV2?client=SOCIAL&type=FAVICON&fallback_opts=TYPE,SIZE,URL&url=https://pornwatch.ws/&size=128",
        "apiVersion": 1,
        "repositoryUrl": "https://github.com/Kraptor123/Cs-GizliKeyif",
        "fileSize": 28020,
        "status": 1,
        "language": "en",
        "authors": [
            "Kraptor"
        ],
        "tvTypes": [
            "NSFW"
        ],
        "version": 10,
        "internalName": "PornWatch",
        "description": "PornWatch - Porn Watch Online Free. Biggest Porn Movies Online Database. Watch and Download Full Porn Movie DVD in High Definition Quality. Latest Collection of Porn Movies DVD Free",
        "url": "https://raw.githubusercontent.com/Kraptor123/Cs-GizliKeyif/builds/PornWatch.cs3",
        "name": "PornWatch"
    },
    {
        "iconUrl": "https://t1.gstatic.com/faviconV2?client=SOCIAL&type=FAVICON&fallback_opts=TYPE,SIZE,URL&url=https://roshy.tv/&size=128",
        "apiVersion": 1,
        "repositoryUrl": "https://github.com/Kraptor123/Cs-GizliKeyif",
        "fileSize": 12074,
        "status": 1,
        "language": "en",
        "authors": [
            "kraptor"
        ],
        "tvTypes": [
            "NSFW"
        ],
        "version": 1,
        "internalName": "RoshyTv",
        "description": "Leaked Uncensored Japanese Adult Videos. Daily Updated Decensored JAV Porn.",
        "url": "https://raw.githubusercontent.com/Kraptor123/Cs-GizliKeyif/builds/RoshyTv.cs3",
        "name": "RoshyTv"
    },
    {
        "iconUrl": "https://en.rusporn.center/favicon.ico",
        "apiVersion": 1,
        "repositoryUrl": "https://github.com/Kraptor123/Cs-GizliKeyif",
        "fileSize": 13053,
        "status": 1,
        "language": "ru",
        "authors": [
            "ByAyzen"
        ],
        "tvTypes": [
            "NSFW"
        ],
        "version": 1,
        "internalName": "Rusporn",
        "description": "Mobile large selection of porn Amateur in HD quality, watch porn. Amateur Only in excellent HD quality for free.",
        "url": "https://raw.githubusercontent.com/Kraptor123/Cs-GizliKeyif/builds/Rusporn.cs3",
        "name": "Rusporn"
    },
    {
        "iconUrl": "http://www.google.com/s2/favicons?domain=sexalarab.com&sz=%size%",
        "apiVersion": 1,
        "repositoryUrl": "https://github.com/Kraptor123/Cs-GizliKeyif",
        "fileSize": 18862,
        "status": 1,
        "language": "ar",
        "authors": [
            "kraptor"
        ],
        "tvTypes": [
            "NSFW"
        ],
        "version": 2,
        "internalName": "SexAlArab",
        "description": "\u0633\u0643\u0633 \u0627\u0644\u0639\u0631\u0628 \u0633\u0643\u0633 \u0645\u062a\u0631\u062c\u0645 \u0627\u0644\u0627\u0641\u0636\u0644 \u0641\u064a \u062a\u0631\u062c\u0645\u0629 \u0627\u0641\u0644\u0627\u0645 \u0627\u0628\u0627\u062d\u0629 \u0627\u062c\u0646\u0628\u064a \u0644\u0644\u0639\u0631\u0628\u064a\u0629 \u0645\u0643\u062a\u0628\u0629 \u0636\u062e\u0645\u0629 \u0645\u062a\u0646\u0648\u0639\u0629 \u0648\u0645\u062a\u062c\u062f\u062f\u0629 \u062a\u0627\u062e\u0630\u0643 \u0627\u0644\u0649 \u0627\u0639\u0645\u0627\u0642 \u0627\u0644\u0645\u062a\u0639\u0629 \u0627\u0644\u062c\u0646\u0633\u064a\u0629 \u0628\u062a\u0635\u0646\u064a\u0641\u0627\u062a \u0645\u062a\u0639\u062f\u062f\u0629 , \u0633\u0643\u0633 \u0645\u062d\u0627\u0631\u0645 , \u0633\u0643\u0633 \u0627\u0645\u0647\u0627\u062a , \u0627\u0641\u0644\u0627\u0645 \u0633\u0643\u0633 - \u0627\u0641\u0644\u0627\u0645 \u062c\u0646\u0633 \u0627\u0628\u0627\u062d\u0647 , \u0627\u0641\u0644\u0627\u0645 \u0633\u0643\u0633 \u0646\u064a\u0643 \u0645\u062a\u0631\u062c\u0645\u0647 , \u0633\u0643\u0633 \u0639\u0631\u0628\u064a \u0645\u062a\u0631\u062c\u0645 - \u0645\u062d\u0627\u0631\u0645 \u0645\u062a\u0631\u062c\u0645 - \u0645\u0648\u0642\u0639 \u0633\u0643\u0633 \u0627\u0644\u0639\u0631\u0628",
        "url": "https://raw.githubusercontent.com/Kraptor123/Cs-GizliKeyif/builds/SexAlArab.cs3",
        "name": "SexAlArab"
    },
    {
        "iconUrl": "https://t3.gstatic.com/faviconV2?client=SOCIAL&type=FAVICON&fallback_opts=TYPE,SIZE,URL&url=https://sextb.net/&size=128",
        "apiVersion": 1,
        "repositoryUrl": "https://github.com/Kraptor123/Cs-GizliKeyif",
        "fileSize": 28410,
        "status": 1,
        "language": "jp",
        "authors": [
            "ByAyzen"
        ],
        "tvTypes": [
            "NSFW"
        ],
        "version": 3,
        "internalName": "SexTB",
        "description": "The Best Free JAV online, JAV DVD online, Stream JAV Online High Quality always updated daily.",
        "url": "https://raw.githubusercontent.com/Kraptor123/Cs-GizliKeyif/builds/SexTB.cs3",
        "name": "SexTB"
    },
    {
        "iconUrl": "https://assets.strpst.com/assets/icons/favicon-196x196.png",
        "apiVersion": 1,
        "repositoryUrl": "https://github.com/Kraptor123/Cs-GizliKeyif",
        "fileSize": 38955,
        "status": 1,
        "language": "en",
        "authors": [
            "kraptor"
        ],
        "tvTypes": [
            "NSFW"
        ],
        "version": 3,
        "internalName": "Stripchat",
        "description": "Watch Naked Models in our Adult Live Sex Cams Community. \u2764\ufe0f It's FREE & No Registration Needed. \ud83d\udd25 4000+ LIVE Cam Girls and Couples are Ready to Chat.",
        "url": "https://raw.githubusercontent.com/Kraptor123/Cs-GizliKeyif/builds/Stripchat.cs3",
        "name": "Stripchat"
    },
    {
        "iconUrl": "https://t3.gstatic.com/faviconV2?client=SOCIAL&type=FAVICON&fallback_opts=TYPE,SIZE,URL&url=https://www.superfilmgeldi1.art/&size=64",
        "apiVersion": 1,
        "repositoryUrl": "https://github.com/Kraptor123/Cs-GizliKeyif",
        "fileSize": 24248,
        "status": 1,
        "language": "tr",
        "authors": [
            "kraptor"
        ],
        "tvTypes": [
            "NSFW"
        ],
        "version": 15,
        "internalName": "SuperErotikGeldi",
        "description": "Superfilmgeldi ve Sinezy Yetiskin kategorileri tek eklentide.",
        "url": "https://raw.githubusercontent.com/Kraptor123/Cs-GizliKeyif/builds/SuperErotikGeldi.cs3",
        "name": "SuperErotikGeldi"
    },
    {
        "iconUrl": "https://t3.gstatic.com/faviconV2?client=SOCIAL&type=FAVICON&fallback_opts=TYPE,SIZE,URL&url=http://sxyprn.com&size=16",
        "apiVersion": 1,
        "repositoryUrl": "https://github.com/Kraptor123/Cs-GizliKeyif",
        "fileSize": 29388,
        "status": 1,
        "language": "en",
        "authors": [
            "ByAyzen"
        ],
        "tvTypes": [
            "NSFW"
        ],
        "version": 4,
        "internalName": "Sxyprn",
        "description": "Enjoy the high quality porn videos, upload original content.",
        "url": "https://raw.githubusercontent.com/Kraptor123/Cs-GizliKeyif/builds/Sxyprn.cs3",
        "name": "Sxyprn"
    },
    {
        "iconUrl": "https://t3.gstatic.com/faviconV2?client=SOCIAL&type=FAVICON&fallback_opts=TYPE,SIZE,URL&url=https://trkhub.fun&size=128",
        "apiVersion": 1,
        "repositoryUrl": "https://github.com/Kraptor123/Cs-GizliKeyif",
        "fileSize": 14280,
        "status": 1,
        "language": "tr",
        "authors": [
            "kraptor"
        ],
        "tvTypes": [
            "NSFW"
        ],
        "version": 4,
        "internalName": "TurkHub",
        "description": "TurkHub.",
        "url": "https://raw.githubusercontent.com/Kraptor123/Cs-GizliKeyif/builds/TurkHub.cs3",
        "name": "TurkHub"
    },
    {
        "iconUrl": "https://t2.gstatic.com/faviconV2?client=SOCIAL&type=FAVICON&fallback_opts=TYPE,SIZE,URL&url=https://turkporno3.cfd&size=128",
        "apiVersion": 1,
        "repositoryUrl": "https://github.com/Kraptor123/Cs-GizliKeyif",
        "fileSize": 31218,
        "status": 1,
        "language": "tr",
        "authors": [
            "Kraptor"
        ],
        "tvTypes": [
            "NSFW"
        ],
        "version": 15,
        "internalName": "TurkPorno",
        "description": "T\u00fcrk if\u015fa.",
        "url": "https://raw.githubusercontent.com/Kraptor123/Cs-GizliKeyif/builds/TurkPorno.cs3",
        "name": "TurkPorno"
    },
    {
        "iconUrl": "http://www.google.com/s2/favicons?domain=https://videocelebs.net",
        "apiVersion": 1,
        "repositoryUrl": "https://github.com/Kraptor123/Cs-GizliKeyif",
        "fileSize": 19324,
        "status": 1,
        "language": "en",
        "authors": [
            "kraptor"
        ],
        "tvTypes": [
            "NSFW"
        ],
        "version": 1,
        "internalName": "VideoCelebs",
        "description": "Database of streaming videos with nude celebs",
        "url": "https://raw.githubusercontent.com/Kraptor123/Cs-GizliKeyif/builds/VideoCelebs.cs3",
        "name": "VideoCelebs"
    },
    {
        "iconUrl": "https://t1.gstatic.com/faviconV2?client=SOCIAL&type=FAVICON&fallback_opts=TYPE,SIZE,URL&url=https://watchporn.to/&size=32",
        "apiVersion": 1,
        "repositoryUrl": "https://github.com/Kraptor123/Cs-GizliKeyif",
        "fileSize": 17414,
        "status": 1,
        "language": "en",
        "authors": [
            "kraptor"
        ],
        "tvTypes": [
            "NSFW"
        ],
        "version": 2,
        "internalName": "WatchPorn",
        "description": "High quality family porn from all over the world especially from manyvids, onlyfans, missax,tabooheat,adulttime and many more. Enjoy MILFs and stepmother with big tits and a lot of mommy roleplay action.",
        "url": "https://raw.githubusercontent.com/Kraptor123/Cs-GizliKeyif/builds/WatchPorn.cs3",
        "name": "WatchPorn"
    },
    {
        "iconUrl": "https://www.google.com/s2/favicons?domain=xhamster.com&sz=%size%",
        "apiVersion": 1,
        "repositoryUrl": "https://github.com/Kraptor123/Cs-GizliKeyif",
        "fileSize": 18772,
        "status": 1,
        "language": "en",
        "authors": [
            "kraptor",
            "coxju",
            "SIX"
        ],
        "tvTypes": [
            "NSFW"
        ],
        "version": 9,
        "internalName": "Xhamster",
        "description": "(VPN) 5 milyondan fazla Porno Videosunu \u00fccretsiz izleyin.",
        "url": "https://raw.githubusercontent.com/Kraptor123/Cs-GizliKeyif/builds/Xhamster.cs3",
        "name": "Xhamster"
    },
    {
        "iconUrl": "https://t0.gstatic.com/faviconV2?client=SOCIAL&type=FAVICON&fallback_opts=TYPE,SIZE,URL&url=https://xmoviesforyou.com/&size=32",
        "apiVersion": 1,
        "repositoryUrl": "https://github.com/Kraptor123/Cs-GizliKeyif",
        "fileSize": 10305,
        "status": 0,
        "language": "en",
        "authors": [
            "kraptor"
        ],
        "tvTypes": [
            "NSFW"
        ],
        "version": 5,
        "internalName": "XMoviesForYou",
        "description": "Free Watch Streaming Premium Porn",
        "url": "https://raw.githubusercontent.com/Kraptor123/Cs-GizliKeyif/builds/XMoviesForYou.cs3",
        "name": "XMoviesForYou"
    },
    {
        "iconUrl": "https://www.google.com/s2/favicons?domain=www.xnalgas.com&sz=%size%",
        "apiVersion": 1,
        "repositoryUrl": "https://github.com/Kraptor123/Cs-GizliKeyif",
        "fileSize": 12100,
        "status": 1,
        "language": "es",
        "authors": [
            "kerimmkirac"
        ],
        "tvTypes": [
            "NSFW"
        ],
        "version": 3,
        "internalName": "XNalgas",
        "description": "Sitio de contenido para adulto donde usted encontrara, Porno Espa\u00f1ol, Latinas XXX, Sexo Anal, Transexuales, Sexo Grupal y V\u00eddeos HD.",
        "url": "https://raw.githubusercontent.com/Kraptor123/Cs-GizliKeyif/builds/XNalgas.cs3",
        "name": "XNalgas"
    },
    {
        "iconUrl": "https://www.google.com/s2/favicons?domain=www.xpaja.net&sz=%size%",
        "apiVersion": 1,
        "repositoryUrl": "https://github.com/Kraptor123/Cs-GizliKeyif",
        "fileSize": 13236,
        "status": 1,
        "language": "es",
        "authors": [
            "kerimmkirac"
        ],
        "tvTypes": [
            "NSFW"
        ],
        "version": 7,
        "internalName": "Xpaja",
        "description": "Xpaja te ofrece v\u00eddeos porno amateur y HD gratis todos los d\u00edas. Tenemos el mejor porno casero del mundo con chicas hermosas, ven disfr\u00fatalo ahora!",
        "url": "https://raw.githubusercontent.com/Kraptor123/Cs-GizliKeyif/builds/Xpaja.cs3",
        "name": "Xpaja"
    },
    {
        "iconUrl": "https://www.google.com/s2/favicons?sz=128&domain=www.xrares.com",
        "apiVersion": 1,
        "repositoryUrl": "https://github.com/Kraptor123/Cs-GizliKeyif",
        "fileSize": 14039,
        "status": 1,
        "language": "en",
        "authors": [
            "kraptor"
        ],
        "tvTypes": [
            "NSFW"
        ],
        "version": 1,
        "internalName": "XRares",
        "description": "XRares.com is a free porn tube for rare scandals, Amateur porn and incest porn. You'll see groping naked, sex in public and much more.",
        "url": "https://raw.githubusercontent.com/Kraptor123/Cs-GizliKeyif/builds/XRares.cs3",
        "name": "XRares"
    },
    {
        "iconUrl": "https://www.google.com/s2/favicons?domain=https://www.xvideos.com&sz=128",
        "jarFileSize": 48759,
        "apiVersion": 1,
        "repositoryUrl": "https://github.com/Kraptor123/Cs-GizliKeyif",
        "fileSize": 14571,
        "status": 1,
        "language": "en",
        "authors": [
            "ByAyzen",
            "SIX"
        ],
        "tvTypes": [
            "NSFW"
        ],
        "version": 7,
        "internalName": "xVideos",
        "jarUrl": "https://raw.githubusercontent.com/Kraptor123/Cs-GizliKeyif/builds/xVideos.jar",
        "description": "xVideos.com is a free hosting service for porn videos.",
        "url": "https://raw.githubusercontent.com/Kraptor123/Cs-GizliKeyif/builds/xVideos.cs3",
        "name": "xVideos"
    },
    {
        "iconUrl": "https://t1.gstatic.com/faviconV2?client=SOCIAL&type=FAVICON&fallback_opts=TYPE,SIZE,URL&url=https://xxxparodyhd.net/&size=16",
        "apiVersion": 1,
        "repositoryUrl": "https://github.com/Kraptor123/Cs-GizliKeyif",
        "fileSize": 23979,
        "status": 1,
        "language": "en",
        "authors": [
            "Kraptor"
        ],
        "tvTypes": [
            "NSFW"
        ],
        "version": 4,
        "internalName": "XXXParodyHD",
        "description": "Enjoy high-quality adult parodies online for free. Browse our extensive collection of the latest parody porn movies available for streaming in HD. Explore the biggest database of adult films from 2023 and 2024 - watch now!",
        "url": "https://raw.githubusercontent.com/Kraptor123/Cs-GizliKeyif/builds/XXXParodyHD.cs3",
        "name": "XXXParodyHD"
    },
    {
        "iconUrl": "https://t2.gstatic.com/faviconV2?client=SOCIAL&type=FAVICON&fallback_opts=TYPE,SIZE,URL&url=https://ytboob.com&size=128",
        "apiVersion": 1,
        "repositoryUrl": "https://github.com/Kraptor123/Cs-GizliKeyif",
        "fileSize": 17725,
        "status": 1,
        "language": "en",
        "authors": [
            "kraptor"
        ],
        "tvTypes": [
            "NSFW"
        ],
        "version": 1,
        "internalName": "YTBoob",
        "description": "YTboob brings you free NSFW videos, nipslips, and nude clips updated daily. Explore top-rated adult content and trending videos in one easy place!",
        "url": "https://raw.githubusercontent.com/Kraptor123/Cs-GizliKeyif/builds/YTBoob.cs3",
        "name": "YTBoob"
    }
]